vuln_structure/__init__.py
vuln_structure/main.py
vuln_structure/prompts.py
vuln_structure-2025.12.22090418.dist-info/METADATA
vuln_structure-2025.12.22090418.dist-info/WHEEL
vuln_structure-2025.12.22090418.dist-info/top_level.txt
vuln_structure-2025.12.22090418.dist-info/RECORD
