Metadata-Version: 2.4
Name: vuln-structure
Version: 2025.12.22090418
Summary: vuln-structure is a package that extracts vulnerability details from raw text and outputs standardized, structured data for security teams.
Author-email: vuln-structure <hi@eugene.plus>
License: MIT
Project-URL: Homepage, https://github.com/chigwell/vuln-structure
Requires-Python: >=3.9
Requires-Dist: langchain-llm7>=0.0.0
Requires-Dist: llmatch-messages>=0.0.0
Requires-Dist: langchain-core>=0.3.0
